theoval/__init__.py
theoval/__main__.py
theoval/binary/__init__.py
theoval/binary/base.py
theoval/binary/convert_scalar.py
theoval/binary/data_loader.py
theoval/binary/experiment.py
theoval/binary/experiment_runner.py
theoval/binary/mcmc.py
theoval/preference/__init__.py
theoval/preference/base.py
theoval/preference/convert_scalar.py
theoval/preference/data_loader.py
theoval/preference/est_mcmc.py
theoval/preference/experiment.py
theoval/preference/experiment_runner.py
theoval/py.typed
theoval/stats/__init__.py
theoval/stats/base.py
theoval/stats/mcmc.py
theoval-0.0.0.dist-info/LICENSE
theoval-0.0.0.dist-info/METADATA
theoval-0.0.0.dist-info/WHEEL
theoval-0.0.0.dist-info/entry_points.txt
theoval-0.0.0.dist-info/RECORD
