Metadata-Version: 2.1
Name: theoval
Version: 0.0.0
Summary: Theoval
Home-page: https://github.com/jderiu/theoval
License: Apache-2.0
Author: Jan Deriu
Author-email: deri@zhaw.ch
Requires-Python: >=3.9,<3.13
Classifier: Development Status :: 2 - Pre-Alpha
Classifier: License :: OSI Approved :: Apache Software License
Classifier: Programming Language :: Python :: 3
Classifier: Programming Language :: Python :: 3.9
Classifier: Programming Language :: Python :: 3.10
Classifier: Programming Language :: Python :: 3.11
Requires-Dist: arviz (>=0.15.1,<0.16.0)
Requires-Dist: click (>=8.0.1)
Requires-Dist: jax (>=0.4.13,<0.5.0)
Requires-Dist: matplotlib (>=3.7.1,<4.0.0)
Requires-Dist: numpy (>=1.25.0,<2.0.0)
Requires-Dist: numpyro (>=0.12.1,<0.13.0)
Requires-Dist: scikit-learn (>=1.3.0,<2.0.0)
Requires-Dist: scipy (>=1.11.1,<2.0.0)
Requires-Dist: tqdm (>=4.65.0,<5.0.0)
Project-URL: Changelog, https://github.com/jderiu/theoval/releases
Project-URL: Documentation, https://theoval.readthedocs.io
Project-URL: Repository, https://github.com/jderiu/theoval
